KishouScrapeDraw/__init__.py
KishouScrapeDraw/createpdf.py
KishouScrapeDraw/drawgraph.py
KishouScrapeDraw/drowweathersymbol.py
KishouScrapeDraw/fetchweathermap.py
KishouScrapeDraw/scraping.py
KishouScrapeDraw/utils.py
kishouscrapedraw-0.1.0.dist-info/licenses/LICENSE
kishouscrapedraw-0.1.0.dist-info/licenses/NOTICE
kishouscrapedraw-0.1.0.dist-info/METADATA
kishouscrapedraw-0.1.0.dist-info/WHEEL
kishouscrapedraw-0.1.0.dist-info/top_level.txt
kishouscrapedraw-0.1.0.dist-info/RECORD
