Metadata-Version: 2.4
Name: KishouScrapeDraw
Version: 0.1.0
Summary: 気象庁(JMA)の天気データを取得・可視化・PDF化する教育向けツール
Home-page: https://github.com/s-kishida/KishouScrapeDraw.git
Author: S.Kishida
Author-email: s.kishida98@gmail.com
License: MIT
Classifier: Programming Language :: Python :: 3
Classifier: License :: OSI Approved :: MIT License
Classifier: Operating System :: OS Independent
Classifier: Intended Audience :: Education
Classifier: Topic :: Education
Classifier: Topic :: Scientific/Engineering :: Atmospheric Science
Classifier: Natural Language :: Japanese
Requires-Python: >=3.8
License-File: LICENSE
License-File: NOTICE
Requires-Dist: matplotlib
Requires-Dist: japanize_matplotlib
Requires-Dist: pandas
Requires-Dist: numpy
Requires-Dist: fpdf
Requires-Dist: requests
Requires-Dist: pdf2image
Requires-Dist: opencv-python-headless
Requires-Dist: PyPDF2
Requires-Dist: qrcode[pil]
Dynamic: author
Dynamic: author-email
Dynamic: classifier
Dynamic: description
Dynamic: description-content-type
Dynamic: home-page
Dynamic: license
Dynamic: license-file
Dynamic: requires-dist
Dynamic: requires-python
Dynamic: summary
